moodlemarking/__about__.py
moodlemarking/__init__.py
moodlemarking/add_margin.py
moodlemarking/moodlezip.py
moodlemarking-0.0.1a0.dist-info/METADATA
moodlemarking-0.0.1a0.dist-info/WHEEL
moodlemarking-0.0.1a0.dist-info/entry_points.txt
moodlemarking-0.0.1a0.dist-info/licenses/LICENSE.txt
moodlemarking-0.0.1a0.dist-info/RECORD
