Metadata-Version: 2.1
Name: moodlemarking
Version: 0.0.1a0
Author-email: Gihan Marasingha <gihan.marasingha@gmail.com>
License-Expression: MIT
License-File: LICENSE.txt
Classifier: Development Status :: 2 - Pre-Alpha
Classifier: Programming Language :: Python
Classifier: Programming Language :: Python :: 3.7
Classifier: Programming Language :: Python :: 3.8
Classifier: Programming Language :: Python :: 3.9
Classifier: Programming Language :: Python :: 3.10
Classifier: Programming Language :: Python :: 3.11
Requires-Python: >=3.7
Requires-Dist: pypdf<4,>=3.16.4
